rediswrapper/__init__.py
rediswrapper/models.py
rediswrapper/storage.py
rediswrapper-0.4.0.post1.dist-info/WHEEL
rediswrapper-0.4.0.post1.dist-info/METADATA
rediswrapper-0.4.0.post1.dist-info/licenses/LICENSE
rediswrapper-0.4.0.post1.dist-info/RECORD
